atlas_schema/__init__.py
atlas_schema/_version.py
atlas_schema/_version.pyi
atlas_schema/enums.py
atlas_schema/methods.py
atlas_schema/py.typed
atlas_schema/schema.py
atlas_schema/typing_compat.py
atlas_schema/utils.py
atlas_schema-0.4.1.dist-info/METADATA
atlas_schema-0.4.1.dist-info/WHEEL
atlas_schema-0.4.1.dist-info/licenses/LICENSE
atlas_schema-0.4.1.dist-info/RECORD
