Metadata-Version: 2.4
Name: atlas-schema
Version: 0.4.1
Summary: Helper python package for ATLAS Common NTuple Analysis work.
Project-URL: Homepage, https://github.com/scipp-atlas/atlas-schema
Project-URL: Bug Tracker, https://github.com/scipp-atlas/atlas-schema/issues
Project-URL: Discussions, https://github.com/scipp-atlas/atlas-schema/discussions
Project-URL: Documentation, https://atlas-schema.readthedocs.io/en/v0.4.1/
Project-URL: Releases, https://github.com/scipp-atlas/atlas-schema/releases
Project-URL: Release Notes, https://atlas-schema.readthedocs.io/en/latest/history.html
Author-email: Giordon Stark <kratsg@gmail.com>
License: 
License-File: LICENSE
Classifier: Development Status :: 1 - Planning
Classifier: Intended Audience :: Developers
Classifier: Intended Audience :: Science/Research
Classifier: License :: OSI Approved :: Apache Software License
Classifier: Operating System :: OS Independent
Classifier: Programming Language :: Python
Classifier: Programming Language :: Python :: 3
Classifier: Programming Language :: Python :: 3 :: Only
Classifier: Programming Language :: Python :: 3.9
Classifier: Programming Language :: Python :: 3.10
Classifier: Programming Language :: Python :: 3.11
Classifier: Programming Language :: Python :: 3.12
Classifier: Topic :: Scientific/Engineering
Classifier: Typing :: Typed
Requires-Python: >=3.9
Requires-Dist: coffea[dask]>=2025.7.0
Requires-Dist: particle>=0.25.0
Provides-Extra: dev
Requires-Dist: pytest-cov>=3; extra == 'dev'
Requires-Dist: pytest>=6; extra == 'dev'
Provides-Extra: docs
Requires-Dist: furo>=2023.08.17; extra == 'docs'
Requires-Dist: intersphinx-registry>=0.2411.17; extra == 'docs'
Requires-Dist: ipywidgets; extra == 'docs'
Requires-Dist: myst-parser>=0.13; extra == 'docs'
Requires-Dist: sphinx-autodoc-typehints; extra == 'docs'
Requires-Dist: sphinx-click; extra == 'docs'
Requires-Dist: sphinx-copybutton!=0.5.1,>=0.3.2; extra == 'docs'
Requires-Dist: sphinx-issues; extra == 'docs'
Requires-Dist: sphinx>=7.0; extra == 'docs'
Provides-Extra: test
Requires-Dist: build; extra == 'test'
Requires-Dist: pylint; extra == 'test'
Requires-Dist: pytest-cov>=3; extra == 'test'
Requires-Dist: pytest>=6; extra == 'test'
Requires-Dist: tbump>=6.7.0; extra == 'test'
Requires-Dist: twine; extra == 'test'
